Queue_Analyzer/__init__.py
Queue_Analyzer-0.9.1.2.dist-info/LICENSE.txt
Queue_Analyzer-0.9.1.2.dist-info/METADATA
Queue_Analyzer-0.9.1.2.dist-info/WHEEL
Queue_Analyzer-0.9.1.2.dist-info/entry_points.txt
Queue_Analyzer-0.9.1.2.dist-info/top_level.txt
Queue_Analyzer-0.9.1.2.dist-info/RECORD
