Metadata-Version: 2.1
Name: Queue-Analyzer
Version: 0.9.1.2
Summary: Generate a distribution for arrival objects and analyze the results from the Dosimis software.
Home-page: https://github.com/dipson94/Queue-Analyzer
Author: Dipson
Author-email: dipson94.coding@gmail.com
License: GNU GPL V3
Classifier: License :: OSI Approved :: GNU General Public License v3 (GPLv3)
Classifier: Programming Language :: Python :: 3.10
Classifier: Operating System :: POSIX :: Linux
Classifier: Operating System :: MacOS :: MacOS X
Classifier: Operating System :: Unix
Requires-Python: >=3.7
License-File: LICENSE.txt
Requires-Dist: matplotlib (>=3.5.1)
Requires-Dist: numpy (>=1.21.5)
Requires-Dist: pycairo (>=1.20.1)
Requires-Dist: pandas (>=2.0.1)
Requires-Dist: PyGObject (>3.42.0)
Provides-Extra: dev
Requires-Dist: pytest (>=7.0) ; extra == 'dev'
